pynecone_debounce_input.py
pynecone_debounce_input-0.3.dist-info/LICENSE
pynecone_debounce_input-0.3.dist-info/METADATA
pynecone_debounce_input-0.3.dist-info/WHEEL
pynecone_debounce_input-0.3.dist-info/top_level.txt
pynecone_debounce_input-0.3.dist-info/RECORD
