Metadata-Version: 2.1
Name: pynecone-debounce-input
Version: 0.3
Summary: Pynecone full-stack framework wrapper around react-debounce-input
Author-email: Masen Furer <m_github@0x26.net>
License: MIT License
Project-URL: Homepage, https://github.com/trivial-intelligence/pynecone-debounce-input
Platform: unix
Platform: linux
Platform: osx
Platform: cygwin
Platform: win32
Classifier: Development Status :: 4 - Beta
Classifier: Intended Audience :: Developers
Classifier: License :: OSI Approved :: MIT License
Classifier: Operating System :: POSIX
Classifier: Operating System :: Microsoft :: Windows
Classifier: Operating System :: MacOS :: MacOS X
Classifier: Topic :: Internet :: WWW/HTTP :: Dynamic Content
Classifier: Topic :: Software Development :: Libraries
Classifier: Topic :: Utilities
Classifier: Programming Language :: Python
Requires-Python: >=3.7
License-File: LICENSE
Requires-Dist: pynecone (~=0.1.30)
